infinitode/__init__.py
infinitode/badge.py
infinitode/core.py
infinitode/errors.py
infinitode/leaderboard.py
infinitode/player.py
infinitode/py.typed
infinitode/score.py
infinitode/utils.py
infinitode.py-1.1.6.dist-info/METADATA
infinitode.py-1.1.6.dist-info/WHEEL
infinitode.py-1.1.6.dist-info/top_level.txt
infinitode.py-1.1.6.dist-info/RECORD
