Metadata-Version: 2.1
Name: infinitode.py
Version: 1.1.6
Summary: A python wrapper for the Infinitode 2 API.
Home-page: https://github.com/Sprylos/infinitode.py
Author: Sprylos
License: MIT
Platform: UNKNOWN
Requires-Dist: aiohttp
Requires-Dist: lxml
Requires-Dist: bs4
